llm_grep.py
llm_grep-0.1.dist-info/METADATA
llm_grep-0.1.dist-info/WHEEL
llm_grep-0.1.dist-info/entry_points.txt
llm_grep-0.1.dist-info/top_level.txt
llm_grep-0.1.dist-info/RECORD
