Metadata-Version: 2.4
Name: llm-grep
Version: 0.1
Summary: LLM plugin for filtering text using semantic regular expressions
Author: Evangelos Lamprou
License: Apache-2.0
Project-URL: Homepage, https://github.com/vagos/llm-grep
Project-URL: Changelog, https://github.com/vagos/llm-grep/releases
Project-URL: Issues, https://github.com/vagos/llm-grep/issues
Project-URL: CI, https://github.com/vagos/llm-grep/actions
Classifier: License :: OSI Approved :: Apache Software License
Requires-Dist: llm>=0.28
Requires-Dist: click!=8.2.1,>=8.0
Provides-Extra: test
Requires-Dist: pytest; extra == "test"
